<?xml version="1.0" encoding="utf-8" ?><dwsync><file name="poster-1.png" server="adampere.com" local="3458144567" remote="12051629912" /><file name="poster-2.png" server="adampere.com" local="3458144614" remote="12051629972" /><file name="poster-4.png" server="adampere.com" local="3458144695" remote="12051629972" /><file name="poster-5.png" server="adampere.com" local="3458144681" remote="12051629972" /><file name="poster-6.png" server="adampere.com" local="3458144651" remote="12051629972" /><file name="poster-7.png" server="adampere.com" local="3458144585" remote="12051629972" /><file name="poster-8.png" server="adampere.com" local="3458144635" remote="12051629972" /><file name="poster-9.jpg" server="adampere.com" local="3458144300" remote="12051629972" /></dwsync>